dout_common-0.1.5.dist-info/METADATA
dout_common-0.1.5.dist-info/WHEEL
dout_common/__init__.py
dout_common/dout_common.cpython-312-x86_64-linux-gnu.so
dout_common-0.1.5.dist-info/RECORD
