Metadata-Version: 2.4
Name: dout-common
Version: 0.1.5
Summary: RFA Hil Testbench
Author: Julius Walczynski, Chee Hang Yong
